anna_mcp_pypi/__init__.py
anna_mcp_pypi-0.1.0.dist-info/WHEEL
anna_mcp_pypi-0.1.0.dist-info/entry_points.txt
anna_mcp_pypi-0.1.0.dist-info/METADATA
anna_mcp_pypi-0.1.0.dist-info/RECORD
