Metadata-Version: 2.3
Name: anna-mcp-pypi
Version: 0.1.0
Summary: Add your description here
Requires-Dist: mcp[cli]>=1.13.0
Requires-Python: >=3.13
